simpletrainer/__init__.py
simpletrainer/common/__init__.py
simpletrainer/common/attrs_extend.py
simpletrainer/common/attrs_extend.pyi
simpletrainer/common/default_settings.py
simpletrainer/common/oprator.py
simpletrainer/common/protocols.py
simpletrainer/common/sign_metric.py
simpletrainer/common/types.py
simpletrainer/components/__init__.py
simpletrainer/components/adversarial/__init__.py
simpletrainer/components/adversarial/fgm.py
simpletrainer/components/basic/__init__.py
simpletrainer/components/basic/best_model_state_tracker.py
simpletrainer/components/basic/file_handler.py
simpletrainer/components/basic/metric_tracker.py
simpletrainer/components/basic/model_watcher.py
simpletrainer/components/basic/save_best_model.py
simpletrainer/components/basic/save_checkpoint.py
simpletrainer/components/basic/scaler_monitor.py
simpletrainer/components/basic/timer.py
simpletrainer/components/debug/__init__.py
simpletrainer/components/debug/try_overfit.py
simpletrainer/components/early_stopping.py
simpletrainer/components/grad/__init__.py
simpletrainer/components/grad/grad_clip.py
simpletrainer/components/grad/grad_penalty.py
simpletrainer/components/label_smoothing.py
simpletrainer/components/lr_scheduler/__init__.py
simpletrainer/components/lr_scheduler/transformers_lr_scheduler.py
simpletrainer/components/metric/__init__.py
simpletrainer/components/metric/torchmetrics_wrapper.py
simpletrainer/components/notification/__init__.py
simpletrainer/components/notification/bark.py
simpletrainer/components/notification/base.py
simpletrainer/components/notification/common.py
simpletrainer/components/notification/wechat.py
simpletrainer/components/terminal/__init__.py
simpletrainer/components/terminal/rich_terminal.py
simpletrainer/components/terminal/tqdm_progress_bar.py
simpletrainer/core/__init__.py
simpletrainer/core/component.py
simpletrainer/core/configs.py
simpletrainer/core/hook.py
simpletrainer/core/info.py
simpletrainer/core/mixins.py
simpletrainer/core/state.py
simpletrainer-0.3.2.post2.dist-info/LICENSE
simpletrainer-0.3.2.post2.dist-info/WHEEL
simpletrainer-0.3.2.post2.dist-info/METADATA
simpletrainer-0.3.2.post2.dist-info/RECORD
